autogen_vertexai_memory/__init__.py
autogen_vertexai_memory/memory/__init__.py
autogen_vertexai_memory/memory/__vertexai_memory.py
autogen_vertexai_memory/tools/__init__.py
autogen_vertexai_memory/tools/__vertexai_memory_tools.py
autogen_vertexai_memory-0.2.0.dist-info/METADATA
autogen_vertexai_memory-0.2.0.dist-info/WHEEL
autogen_vertexai_memory-0.2.0.dist-info/licenses/LICENSE
autogen_vertexai_memory-0.2.0.dist-info/RECORD
