Metadata-Version: 2.4
Name: autogen-vertexai-memory
Version: 0.2.0
Summary: VertexAI Memory integration for Autogen agents
License: MIT
License-File: LICENSE
Keywords: autogen,vertexai,memory,ai,agents
Author: thelaycon
Author-email: tobitobitobiwhy@gmail.com
Requires-Python: >=3.10,<4.0
Classifier: Development Status :: 3 - Alpha
Classifier: Intended Audience :: Developers
Classifier: License :: OSI Approved :: MIT License
Classifier: Programming Language :: Python :: 3
Classifier: Programming Language :: Python :: 3.10
Classifier: Programming Language :: Python :: 3.11
Classifier: Programming Language :: Python :: 3.12
Classifier: Programming Language :: Python :: 3.13
Classifier: Programming Language :: Python :: 3.14
Requires-Dist: autogen-core (>=0.7.5,<0.8.0)
Requires-Dist: google-cloud-aiplatform (==1.115.0)
Requires-Dist: pydantic (>=2.12.3,<3.0.0)
Project-URL: Documentation, https://github.com/thelaycon/autogen-vertexai-memory
Project-URL: Homepage, https://github.com/thelaycon/autogen-vertexai-memory
Project-URL: Repository, https://github.com/thelaycon/autogen-vertexai-memory
